ovd_client/__init__.py
ovd_client/client.py
ovd_client/vmd.py
openvr_virtual_driver_client-0.0.6.dist-info/METADATA
openvr_virtual_driver_client-0.0.6.dist-info/WHEEL
openvr_virtual_driver_client-0.0.6.dist-info/RECORD
