Metadata-Version: 2.4
Name: openvr-virtual-driver-client
Version: 0.0.6
Summary: Python client for OpenVR virtual driver
Project-URL: Homepage, https://github.com/Project-NEURIA/openvr-virtual-driver
Classifier: Development Status :: 3 - Alpha
Classifier: License :: OSI Approved :: MIT License
Classifier: Programming Language :: Python :: 3.12
Classifier: Programming Language :: Python :: 3.13
Requires-Python: >=3.12
Requires-Dist: numpy>=2.0.0
Requires-Dist: pygame-ce>=2.5.0
